.gitignore
setup.py
test_uh.py
uh/__init__.py
uh/base.py
uh/fs.py
uh/uuid4fs.py
uh.egg-info/PKG-INFO
uh.egg-info/SOURCES.txt
uh.egg-info/dependency_links.txt
uh.egg-info/requires.txt
uh.egg-info/top_level.txt