Metadata-Version: 1.0
Name: uh
Version: 0.1.3
Summary: Upload Handler
Home-page: https://github.com/dmonroy/uh
Author: Darwin Monroy
Author-email: contact@darwinmonroy.com
License: MIT License
Platform: UNKNOWN
